prooverlap/Create_bed_genomicRegions.R
prooverlap/Density_plot.R
prooverlap/Heatmap.R
prooverlap/RankPlot.R
prooverlap/__init__.py
prooverlap/prooverlap.py
prooverlap-0.1.2.dist-info/licenses/LICENSE
prooverlap-0.1.2.dist-info/METADATA
prooverlap-0.1.2.dist-info/WHEEL
prooverlap-0.1.2.dist-info/entry_points.txt
prooverlap-0.1.2.dist-info/top_level.txt
prooverlap-0.1.2.dist-info/RECORD
