Metadata-Version: 2.4
Name: prooverlap
Version: 0.1.2
Summary: Assessing feature proximity/overlap and testing statistical significance from genomic intervals
Home-page: https://github.com/ngualand/ProOvErlap
Author: Nicolò Gualandi, Alessio Bertozzo, Claudio Brancolini
Author-email: Nicolò Gualandi <nicolo.gualandi@uniud.it>, Alessio Bertozzo <bertozzo.alessio@spes.uniud.it>, Claudio Brancolini <claudio.brancolini@uniud.it>
License: GPL-3.0
Project-URL: Homepage, https://github.com/ngualand/ProOvErlap
Project-URL: Source, https://github.com/ngualand/ProOvErlap
Project-URL: Bug Tracker, https://github.com/ngualand/ProOvErlap/issues
Requires-Python: >=3.7
License-File: LICENSE
Requires-Dist: biopython
Requires-Dist: pandas
Requires-Dist: scipy
Requires-Dist: pybedtools
Requires-Dist: numpy
Dynamic: author
Dynamic: home-page
Dynamic: license-file
Dynamic: requires-python
